{
    "kcal": "100",
    "prot": "100",
    "calc": "100",
    "carbs": "100",
    "name": "Spaghettis carbonara",
	"description" : "TEMPS TOTAL : 25 MIN Préparation : 10 min Cuisson : 15 min \nEtape 1 : Faire cuire les pâtes le temps indiqué sur le paquet. \nEtape 2 : Faire revenir les lardons sans matière grasse dans une poêle anti-adhésive. \nEtape 3 : Une fois les lardons cuits, y ajouter la crème fraîche et le parmesan. Saler et poivrer. \nEtape 4 : Faire réduire une quinzaine de minutes à feu moyen en mélangeant de temps en temps afin que la crème n'attache pas. \nEtape 5 : Une fois que la sauce a la consistance voulue (cest-à-dire dès quelle nappe la cuillère), la rétirer du feu. \nEtape 6 : Ajouter le jaune d'oeuf battu et mélanger énergiquement. \nEtape 7 : Ajouter à ce mélange les pâtes égouttées (tout en conservant un tout petit peu d'eau de cuisson). \nEtape 8 : Mélanger le tout et servir!",
    "difficulty": "0",
    "dishesSize": "2",
    
    "quantities" : [
        "250","300", "20", "30", "1", "", ""
    ]
    
}